<?xml version="1.0" encoding="UTF-8"?>
<board src="resources/level0.png">
    <pushActivatedSwitch id="push" slot="0" direction="toLeft" activeTimeMs="30000">
        <key slot="6" name="key1"/>
        <door id="door" slot="1" keyName="key1" position="vertical">
            <transmitControlTrigger sourceId="push" targetId="door" action="both" />
        </door>
    </pushActivatedSwitch>
    <pushActivatedSwitch  slot="3" direction="toRight" activeTimeMs="1000" />
    <pushActivatedSwitch  slot="4" direction="toTop" activeTimeMs="1000" />
    <pushActivatedSwitch  slot="5" direction="toBottom" activeTimeMs="1000" />
</board>
